calendary/__init__.py
calendary/calendary.py
calendary-0.3.13.dist-info/DESCRIPTION.rst
calendary-0.3.13.dist-info/METADATA
calendary-0.3.13.dist-info/RECORD
calendary-0.3.13.dist-info/WHEEL
calendary-0.3.13.dist-info/metadata.json
calendary-0.3.13.dist-info/top_level.txt
