Metadata-Version: 2.0
Name: calendary
Version: 0.3.13
Summary: Python calendar helper.
Home-page: https://github.com/DavidHickman/calendary
Author: David Hickman
Author-email: davidhickman13@gmail.com
License: BSD license
Keywords: calendary
Platform: UNKNOWN
Classifier: Development Status :: 2 - Pre-Alpha
Classifier: Intended Audience :: Developers
Classifier: License :: OSI Approved :: BSD License
Classifier: Natural Language :: English
Classifier: Programming Language :: Python :: 2
Classifier: Programming Language :: Python :: 2.6
Classifier: Programming Language :: Python :: 2.7
Classifier: Programming Language :: Python :: 3
Classifier: Programming Language :: Python :: 3.3
Classifier: Programming Language :: Python :: 3.4
Classifier: Programming Language :: Python :: 3.5
